distributions/Binomialdistribution.py
distributions/Gaussiandistribution.py
distributions/Generaldistribution.py
distributions/__init__.py
zzhprob-0.3.dist-info/METADATA
zzhprob-0.3.dist-info/WHEEL
zzhprob-0.3.dist-info/top_level.txt
zzhprob-0.3.dist-info/RECORD
